gphoto2/__init__.py
gphoto2/__main__.py
gphoto2/_abilities_list.cpython-39-aarch64-linux-gnu.so
gphoto2/_camera.cpython-39-aarch64-linux-gnu.so
gphoto2/_context.cpython-39-aarch64-linux-gnu.so
gphoto2/_file.cpython-39-aarch64-linux-gnu.so
gphoto2/_filesys.cpython-39-aarch64-linux-gnu.so
gphoto2/_list.cpython-39-aarch64-linux-gnu.so
gphoto2/_port.cpython-39-aarch64-linux-gnu.so
gphoto2/_port_info_list.cpython-39-aarch64-linux-gnu.so
gphoto2/_port_log.cpython-39-aarch64-linux-gnu.so
gphoto2/_result.cpython-39-aarch64-linux-gnu.so
gphoto2/_version.cpython-39-aarch64-linux-gnu.so
gphoto2/_widget.cpython-39-aarch64-linux-gnu.so
gphoto2/abilities_list.py
gphoto2/camera.py
gphoto2/context.py
gphoto2/file.py
gphoto2/filesys.py
gphoto2/list.py
gphoto2/port.py
gphoto2/port_info_list.py
gphoto2/port_log.py
gphoto2/result.py
gphoto2/version.py
gphoto2/widget.py
gphoto2/examples/README.rst
gphoto2/examples/cam-conf-view-gui.py
gphoto2/examples/camera-config-gui.py
gphoto2/examples/camera-summary.py
gphoto2/examples/capture-image.py
gphoto2/examples/choose-camera.py
gphoto2/examples/clear-space.py
gphoto2/examples/context_with_callbacks.py
gphoto2/examples/copy-chunks.py
gphoto2/examples/copy-data.py
gphoto2/examples/copy-files.py
gphoto2/examples/error_handling.py
gphoto2/examples/focus-gui.py
gphoto2/examples/get-camera-clock.py
gphoto2/examples/get-capture-target.py
gphoto2/examples/gphoto2_version.py
gphoto2/examples/list-cameras.py
gphoto2/examples/list-files.py
gphoto2/examples/log_events.py
gphoto2/examples/preview-image.py
gphoto2/examples/read-exif-exifread.py
gphoto2/examples/read-exif-gexiv2.py
gphoto2/examples/set-camera-clock.py
gphoto2/examples/set-capture-target.py
gphoto2/examples/time_lapse.py
gphoto2/examples/wait-for-event.py
gphoto2/libgphoto2/libgphoto2.so.6
gphoto2/libgphoto2/libgphoto2_port.so.12
gphoto2/libgphoto2/camlibs/ax203.so
gphoto2/libgphoto2/camlibs/canon.so
gphoto2-2.6.3.dist-info/METADATA
gphoto2-2.6.3.dist-info/WHEEL
gphoto2-2.6.3.dist-info/top_level.txt
gphoto2-2.6.3.dist-info/RECORD
gphoto2-2.6.3.dist-info/licenses/LICENSE.txt
