Metadata-Version: 2.1
Name: gphoto2
Version: 2.6.3
Summary: Python interface to libgphoto2
Home-page: https://github.com/jim-easterbrook/python-gphoto2
Author: Jim Easterbrook
Author-email: jim@jim-easterbrook.me.uk
License: GNU LGPL
Platform: POSIX
Platform: MacOS
Classifier: Development Status :: 5 - Production/Stable
Classifier: Intended Audience :: Developers
Classifier: License :: OSI Approved :: GNU Lesser General Public License v3 or later (LGPLv3+)
Classifier: Operating System :: MacOS
Classifier: Operating System :: MacOS :: MacOS X
Classifier: Operating System :: POSIX
Classifier: Operating System :: POSIX :: BSD :: FreeBSD
Classifier: Operating System :: POSIX :: BSD :: NetBSD
Classifier: Operating System :: POSIX :: Linux
Classifier: Programming Language :: Python :: 3
Classifier: Topic :: Multimedia
Classifier: Topic :: Multimedia :: Graphics
Classifier: Topic :: Multimedia :: Graphics :: Capture
License-File: LICENSE.txt
